{
    "equipment_density": 10,
    "equipment_density_unit": "W/m2",
    "schedule_name": "office",
    "CO2_sensor": "no",
    "design_people_density": 10,
    "design_people_density_unit": "m2/pax",
    "typical_people_density": 10,
    "typical_people_density_unit": "m2/pax",
    "percent_days_peak_occupancy": 100,
    "lift_energy": 1,
    "lift_energy_unit": "W/m2",
    "facade_lighting": 1,
    "facade_lighting_unit": "W/m2/facade",
    "landscape_lighting": 1,
    "landscape_lighting_unit": "W/m2",
    "carpark_lighting": 1,
    "carpark_lighting_unit": "W/m2",
    "carpark_ventilation": 1,
    "carpark_ventilation_unit": "W/m2",
    "fresh_air_rate": 0.3,
    "fresh_air_rate_unit": "l/s/m2",
    "thermal_mass": 200,
    "thermal_mass_unit": "kg/m2" 
     
} 